perceptic_core_client/__init__.py
perceptic_core_client/api_client.py
perceptic_core_client/api_response.py
perceptic_core_client/configuration.py
perceptic_core_client/exceptions.py
perceptic_core_client/rest.py
perceptic_core_client/api/__init__.py
perceptic_core_client/api/citations_resource_api.py
perceptic_core_client/api/connection_resource_api.py
perceptic_core_client/api/file_system_contents_resource_api.py
perceptic_core_client/api/file_system_resource_api.py
perceptic_core_client/api/indexer_resource_api.py
perceptic_core_client/api/indexing_schedule_resource_api.py
perceptic_core_client/api/indexing_task_resource_api.py
perceptic_core_client/api/tag_resource_api.py
perceptic_core_client/api/uri_resource_api.py
perceptic_core_client/api/user_resource_api.py
perceptic_core_client/api/worker_resource_api.py
perceptic_core_client/models/__init__.py
perceptic_core_client/models/action_type.py
perceptic_core_client/models/add_tag_to_file_request.py
perceptic_core_client/models/azure_blob_connection_settings_api_dto.py
perceptic_core_client/models/azure_blob_file_system_root_metadata_api_dto.py
perceptic_core_client/models/biotech_analysis_api_dto.py
perceptic_core_client/models/biotech_analysis_image_annotated_citation_api_dto.py
perceptic_core_client/models/bulk_get_citations_request.py
perceptic_core_client/models/bulk_get_citations_response.py
perceptic_core_client/models/citation_api_dto.py
perceptic_core_client/models/citation_metadata_api_dto.py
perceptic_core_client/models/connection_api_dto.py
perceptic_core_client/models/connection_settings_api_dto.py
perceptic_core_client/models/create_connection_request.py
perceptic_core_client/models/create_connection_response.py
perceptic_core_client/models/create_file_system_response.py
perceptic_core_client/models/create_folder_request.py
perceptic_core_client/models/create_folder_response.py
perceptic_core_client/models/create_folder_response_v2.py
perceptic_core_client-0.51.3.dist-info/METADATA
perceptic_core_client-0.51.3.dist-info/WHEEL
perceptic_core_client-0.51.3.dist-info/top_level.txt
perceptic_core_client-0.51.3.dist-info/RECORD
