Metadata-Version: 2.4
Name: perceptic-core-client
Version: 0.51.3
Summary: Python client for Perceptic Core
Author-email: Your Name <you@example.com>
License: Proprietary
Classifier: Programming Language :: Python :: 3
Requires-Python: >=3.9
Requires-Dist: urllib3<3.0.0,>=2.1.0
Requires-Dist: python-dateutil>=2.8.2
Requires-Dist: pydantic>=2
Requires-Dist: typing-extensions>=4.7.1
Provides-Extra: dev
Requires-Dist: pytest; extra == "dev"
Requires-Dist: pytest-cov; extra == "dev"
Requires-Dist: ruff; extra == "dev"
Requires-Dist: mypy; extra == "dev"
Requires-Dist: build; extra == "dev"
Requires-Dist: requests; extra == "dev"
